cloudeventful/__init__.py
cloudeventful/_cloud_event.py
cloudeventful/_cloud_event_doc.py
cloudeventful/_cloud_eventful.py
cloudeventful/py.typed
cloudeventful-3.0.0.dist-info/LICENSE
cloudeventful-3.0.0.dist-info/METADATA
cloudeventful-3.0.0.dist-info/WHEEL
cloudeventful-3.0.0.dist-info/RECORD
