Metadata-Version: 2.1
Name: cloudeventful
Version: 3.0.0
Summary: Broker agnostic library to associate JSON Schemas to message broker topics.
Home-page: https://gitlab.com/mburkard/cloud-eventful
License: MIT
Author: Matthew Burkard
Author-email: matthewjburkard@gmail.com
Requires-Python: >=3.9,<4.0
Classifier: Intended Audience :: Developers
Classifier: License :: OSI Approved :: MIT License
Classifier: Programming Language :: Python :: 3
Classifier: Programming Language :: Python :: 3.9
Classifier: Programming Language :: Python :: 3.10
Classifier: Programming Language :: Python :: 3.11
Classifier: Programming Language :: Python :: 3.12
Classifier: Topic :: Software Development
Classifier: Topic :: Software Development :: Libraries
Classifier: Topic :: Software Development :: Libraries :: Python Modules
Classifier: Typing :: Typed
Requires-Dist: pydantic (>=2.5.1,<3.0.0)
Project-URL: Repository, https://gitlab.com/mburkard/cloud-eventful
